face_parsing/__init__.py
face_parsing/model.py
face_parsing/resnet.py
dg_util_face_parsing-0.0.1.dist-info/WHEEL
dg_util_face_parsing-0.0.1.dist-info/METADATA
dg_util_face_parsing-0.0.1.dist-info/RECORD
